{
  "indexes": [
    {
      "collectionGroup": "notification",
      "queryScope": "COLLECTION",
      "fields": [
        {
          "fieldPath": "user_ref",
          "order": "ASCENDING"
        },
        {
          "fieldPath": "time",
          "order": "DESCENDING"
        }
      ]
    },
    {
      "collectionGroup": "notification",
      "queryScope": "COLLECTION",
      "fields": [
        {
          "fieldPath": "public",
          "order": "ASCENDING"
        },
        {
          "fieldPath": "time",
          "order": "DESCENDING"
        }
      ]
    },
    {
      "collectionGroup": "orders",
      "queryScope": "COLLECTION",
      "fields": [
        {
          "fieldPath": "driver",
          "order": "ASCENDING"
        },
        {
          "fieldPath": "order_status",
          "order": "ASCENDING"
        },
        {
          "fieldPath": "order_number",
          "order": "DESCENDING"
        }
      ]
    }
  ],
  "fieldOverrides": [
    {
      "collectionGroup": "offers",
      "fieldPath": "user_offer",
      "indexes": [
        {
          "order": "ASCENDING",
          "queryScope": "COLLECTION_GROUP"
        }
      ]
    },
    {
      "collectionGroup": "fcm_tokens",
      "fieldPath": "fcm_token",
      "indexes": [
        {
          "order": "ASCENDING",
          "queryScope": "COLLECTION_GROUP"
        }
      ]
    }
  ]
}